smartbulk_connector/__init__.py
smartbulk_connector/_api.py
smartbulk_connector/_connector.py
smartbulk_connector/_constants.py
smartbulk_connector/_utils.py
smartbulk_connector-1.0.5.dist-info/METADATA
smartbulk_connector-1.0.5.dist-info/WHEEL
smartbulk_connector-1.0.5.dist-info/top_level.txt
smartbulk_connector-1.0.5.dist-info/RECORD
