Metadata-Version: 2.1
Name: smartbulk_connector
Version: 1.0.5
Summary: BioTuring Smartbulk Connector
Home-page: https://app.bioturing.com/smartbulk
Author: BioTuring
Author-email: support@bioturing.com
Requires-Python: >=3.8, <3.12
Requires-Dist: pydantic==2.7.2
Requires-Dist: requests==2.32.3
Requires-Dist: tqdm==4.66.4
Requires-Dist: pandas
Requires-Dist: numpy
